intrade/__init__.py
intrade/intrade.py
intrade-0.1.3.dist-info/METADATA
intrade-0.1.3.dist-info/WHEEL
intrade-0.1.3.dist-info/licenses/LICENSE
intrade-0.1.3.dist-info/RECORD
