Metadata-Version: 2.4
Name: intrade
Version: 0.1.3
Summary: The intrade Python package provides a unified toolkit for international trade empirical analysis.
Project-URL: Homepage, https://github.com/Juan-de-Lucio/REPO
Project-URL: Issues, https://github.com/Juan-de-Lucio/REPO/issues
Author-email: Juan de Lucio & Francisco Requena <Juan.deLucio@uah.es>
License: MIT License
License-File: LICENSE
Requires-Python: >=3.9
